zprocess/__init__.py
zprocess/__version__.py
zprocess/clientserver.py
zprocess/cryptoproxy.py
zprocess/makesecret.py
zprocess/process_class_wrapper.py
zprocess/process_tree.py
zprocess/security.py
zprocess/tasks.py
zprocess/utils.py
zprocess/examples/example_child.py
zprocess/examples/example_parent.py
zprocess/examples/processclass_example.py
zprocess/examples/processclass_remote_example.py
zprocess/locking/__init__.py
zprocess/locking/__main__.py
zprocess/remote/__init__.py
zprocess/remote/__main__.py
zprocess/remote/curses_server.py
zprocess/remote/server.py
zprocess/socks/__init__.py
zprocess/socks/server.py
zprocess/zlock/__init__.py
zprocess/zlock/__main__.py
zprocess/zlock/server.py
zprocess/zlog/__init__.py
zprocess/zlog/__main__.py
zprocess/zlog/server.py
zprocess-2.26.1.dist-info/LICENSE.txt
zprocess-2.26.1.dist-info/METADATA
zprocess-2.26.1.dist-info/WHEEL
zprocess-2.26.1.dist-info/top_level.txt
zprocess-2.26.1.dist-info/RECORD
