Metadata-Version: 2.1
Name: zprocess
Version: 2.26.1
Summary: A set of utilities for multiprocessing using zeromq
Author-email: Christopher Billington <chrisjbillington@gmail.com>
License: Copyright (c) 2013, Christopher Billington
Project-URL: Homepage, https://github.com/chrisjbillington/zprocess
Project-URL: Documentation, https://github.com/chrisjbillington/zprocess
Project-URL: Repository, https://github.com/chrisjbillington/zprocess
Project-URL: Downloads, https://pypi.org/project/zprocess/
Project-URL: Tracker, https://github.com/chrisjbillington/zprocess/issues
Keywords: multiprocessing,IPC,zeromq
Classifier: License :: OSI Approved :: BSD License
Classifier: Programming Language :: Python :: 3 :: Only
Requires-Python: >=3.8
License-File: LICENSE.txt
Requires-Dist: setuptools_scm
Requires-Dist: pyzmq
Requires-Dist: pywin32; sys_platform == "win32"
Requires-Dist: windows-curses; sys_platform == "win32"
Provides-Extra: test
Requires-Dist: pytest; extra == "test"
Requires-Dist: pytest-cov; extra == "test"
